{
  "annotations": {
    "changelogDate": "20250111122119"
  },
  "dto": "mapstruct",
  "fields": [
    {
      "fieldName": "Name",
      "fieldType": "String",
      "fieldValidateRules": ["required"]
    },
    {
      "fieldName": "externalId",
      "fieldType": "Integer",
      "fieldValidateRules": ["required"]
    },
    {
      "fieldName": "uuid",
      "fieldType": "String",
      "fieldValidateRules": ["required", "unique"]
    },
    {
      "fieldName": "dateCreated",
      "fieldType": "Instant",
      "fieldValidateRules": ["required"]
    },
    {
      "fieldName": "dateModified",
      "fieldType": "Instant",
      "fieldValidateRules": ["required"]
    },
    {
      "fieldName": "dateSynched",
      "fieldType": "Instant",
      "fieldValidateRules": ["required"]
    },
    {
      "fieldName": "dateDeleted",
      "fieldType": "Instant"
    }
  ],
  "jpaMetamodelFiltering": false,
  "name": "HiveType",
  "pagination": "pagination",
  "readOnly": false,
  "relationships": [
    {
      "otherEntityField": "id",
      "otherEntityName": "user",
      "relationshipName": "user",
      "relationshipSide": "left",
      "relationshipType": "many-to-one"
    }
  ],
  "searchEngine": "no",
  "service": "serviceClass"
}
